proverbot/__init__.py
proverbot/talk/__init__.py
proverbot/talk/proverb.py
proverbot-0.1.0.dist-info/METADATA
proverbot-0.1.0.dist-info/WHEEL
proverbot-0.1.0.dist-info/top_level.txt
proverbot-0.1.0.dist-info/RECORD
