Metadata-Version: 2.1
Name: proverbot
Version: 0.1.0
Summary: A complete package to bring fun and repartee
Author: astro__pat
